ocsort/__init__.py
ocsort/association.py
ocsort/kalmanfilter.py
ocsort/tracker.py
techainer_ocsort-0.1.dist-info/LICENSE
techainer_ocsort-0.1.dist-info/METADATA
techainer_ocsort-0.1.dist-info/WHEEL
techainer_ocsort-0.1.dist-info/top_level.txt
techainer_ocsort-0.1.dist-info/RECORD
