Metadata-Version: 2.1
Name: techainer-ocsort
Version: 0.1
Summary: "Horus's general object tracker"
Home-page: https://techainer.com
Download-URL: https://github.com/Techainer/ocsort
Author: Techainer
Author-email: admin@techainer.com
Maintainer: gran
Maintainer-email: gran@techainer.com
Project-URL: Documentation, https://techainer.com
Project-URL: Source, https://github.com/Techainer/ocsort
Keywords: horus,object-tracker,computer-vision,machine-learning
Classifier: Development Status :: 4 - Beta
Classifier: Programming Language :: Python :: 3
Classifier: Programming Language :: Python :: 3.6
Classifier: Programming Language :: Python :: 3.7
Classifier: Programming Language :: Python :: 3.8
Requires-Python: >=3.6.*
License-File: LICENSE
Requires-Dist: filterpy
Requires-Dist: numpy
Provides-Extra: test
Requires-Dist: coverage ; extra == 'test'
